mle_monitor/__init__.py
mle_monitor/_version.py
mle_monitor/mle_dashboard.py
mle_monitor/mle_protocol.py
mle_monitor/mle_resource.py
mle_monitor/dashboard/__init__.py
mle_monitor/dashboard/layout.py
mle_monitor/dashboard/update.py
mle_monitor/dashboard/components/__init__.py
mle_monitor/dashboard/components/plots.py
mle_monitor/dashboard/components/protocol.py
mle_monitor/dashboard/components/usage.py
mle_monitor/protocol/__init__.py
mle_monitor/protocol/add.py
mle_monitor/protocol/gcs_sync.py
mle_monitor/protocol/load.py
mle_monitor/protocol/summary.py
mle_monitor/protocol/tables.py
mle_monitor/resource/__init__.py
mle_monitor/resource/gcp.py
mle_monitor/resource/local.py
mle_monitor/resource/sge.py
mle_monitor/resource/slurm.py
mle_monitor/utils/__init__.py
mle_monitor/utils/gcs_zip.py
mle_monitor/utils/helpers.py
mle_monitor/utils/tracker.py
mle_monitor-0.0.2.dist-info/LICENSE
mle_monitor-0.0.2.dist-info/METADATA
mle_monitor-0.0.2.dist-info/WHEEL
mle_monitor-0.0.2.dist-info/top_level.txt
mle_monitor-0.0.2.dist-info/RECORD
