Metadata-Version: 2.1
Name: mle-monitor
Version: 0.0.2
Summary: Machine Learning Experiment Resource Monitoring
Home-page: https://github.com/mle-infrastructure/mle-monitor
Download-URL: https://github.com/mle-infrastructure/mle-monitor/archive/v0.0.2.tar.gz
Author: Robert Tjarko Lange
Author-email: robertlange0@gmail.com
Platform: any
Classifier: Programming Language :: Python :: 3.6
Classifier: Programming Language :: Python :: 3.7
Classifier: Programming Language :: Python :: 3.8
Classifier: Programming Language :: Python :: 3.9
Classifier: License :: OSI Approved :: MIT License
Classifier: Operating System :: OS Independent
Classifier: Topic :: Scientific/Engineering :: Artificial Intelligence
Requires-Python: >=3.6
License-File: LICENSE
Requires-Dist: pyyaml
Requires-Dist: commentjson
Requires-Dist: dotmap
Requires-Dist: numpy
Requires-Dist: pandas
Requires-Dist: rich
Requires-Dist: pickledb
Requires-Dist: plotext (==4.0.0)
Requires-Dist: Pillow
Provides-Extra: examples
Requires-Dist: mle-logging ; extra == 'examples'
Requires-Dist: mle-hyperopt ; extra == 'examples'
Provides-Extra: full
Requires-Dist: psutil ; extra == 'full'
Requires-Dist: gputil ; extra == 'full'
Requires-Dist: google-cloud-storage ; extra == 'full'
Requires-Dist: GitPython ; extra == 'full'
